pykakaopay/__init__.py
pykakaopay/auth.py
pykakaopay/error.py
pykakaopay/recurring_payment.py
pykakaopay/single_payment.py
pykakaopay-0.1.1.dist-info/LICENSE
pykakaopay-0.1.1.dist-info/WHEEL
pykakaopay-0.1.1.dist-info/METADATA
pykakaopay-0.1.1.dist-info/RECORD
