Metadata-Version: 2.1
Name: pykakaopay
Version: 0.1.1
Summary: 
Author: sehwan505
Author-email: sehwan505@gmail.com
Requires-Python: >=3.8,<4.0
Classifier: Programming Language :: Python :: 3
Classifier: Programming Language :: Python :: 3.8
Classifier: Programming Language :: Python :: 3.9
Requires-Dist: requests (>=2.27.1,<3.0.0)
